{"data":{"allMarkdownRemark":{"edges":[{"node":{"id":"a3510664-99ac-557c-8cbb-530251bbda40","htmlAst":{"type":"root","children":[{"type":"element","tagName":"h1","properties":{},"children":[{"type":"text","value":"Frontend-Developer"}]},{"type":"text","value":"\n"},{"type":"element","tagName":"h2","properties":{},"children":[{"type":"text","value":"info"}]},{"type":"text","value":"\n"},{"type":"element","tagName":"ul","properties":{},"children":[{"type":"text","value":"\n"},{"type":"element","tagName":"li","properties":{},"children":[{"type":"text","value":"Company: Senesys"}]},{"type":"text","value":"\n"},{"type":"element","tagName":"li","properties":{},"children":[{"type":"text","value":"Project: Fitstarter"}]},{"type":"text","value":"\n"},{"type":"element","tagName":"li","properties":{},"children":[{"type":"text","value":"Technical stack and tools: JavaScript(ES6/7), React.js, Redux.js, recompose, reselect, redux-saga, RxJS, lodash, jest, enzyme, next.js, SCSS, Worker(-workers, -socket), css-in-js, webpack/babel, npm/yarn, fetch, HTTP, HTML5, git-flow, EsLint"}]},{"type":"text","value":"\n"}]},{"type":"text","value":"\n"},{"type":"element","tagName":"h2","properties":{},"children":[{"type":"text","value":"tasks"}]},{"type":"text","value":"\n"},{"type":"element","tagName":"ul","properties":{},"children":[{"type":"text","value":"\n"},{"type":"element","tagName":"li","properties":{},"children":[{"type":"text","value":"Performed SSR application with next.js and React/Redux"}]},{"type":"text","value":"\n"},{"type":"element","tagName":"li","properties":{},"children":[{"type":"text","value":"Make smart and dumb Components (React.js)"}]},{"type":"text","value":"\n"},{"type":"element","tagName":"li","properties":{},"children":[{"type":"text","value":"Architectural solutions client store (Redux store)"}]},{"type":"text","value":"\n"},{"type":"element","tagName":"li","properties":{},"children":[{"type":"text","value":"Created Router for Application (modal/permissions/auth)"}]},{"type":"text","value":"\n"},{"type":"element","tagName":"li","properties":{},"children":[{"type":"text","value":"Fetching data from Rest API"}]},{"type":"text","value":"\n"}]}],"data":{"quirksMode":false}},"frontmatter":{"title":"Frontend-Developer","path":"/job/senesys","date":"05-March-2018 - 31-January-2019"}}},{"node":{"id":"c671acc4-ad30-5e78-a5ad-d95c5830879f","htmlAst":{"type":"root","children":[{"type":"element","tagName":"h1","properties":{},"children":[{"type":"text","value":"Web-Developer"}]},{"type":"text","value":"\n"},{"type":"element","tagName":"h2","properties":{},"children":[{"type":"text","value":"info"}]},{"type":"text","value":"\n"},{"type":"element","tagName":"ul","properties":{},"children":[{"type":"text","value":"\n"},{"type":"element","tagName":"li","properties":{},"children":[{"type":"text","value":"Company: Yondermusic"}]},{"type":"text","value":"\n"},{"type":"element","tagName":"li","properties":{},"children":[{"type":"text","value":"Project: Yonder-music (web), Portal-Tools"}]},{"type":"text","value":"\n"},{"type":"element","tagName":"li","properties":{},"children":[{"type":"text","value":"Technical stack and tools: JavaScript(ES6/7), React.js, Redux.js, React-Router@4, SASS/SCSS, Gulp.js/Webpack.js/babel, npm/yarn, fetch, HTTP, HTML, RxJS, Git-flow, EsLint, lodash"}]},{"type":"text","value":"\n"}]},{"type":"text","value":"\n"},{"type":"element","tagName":"h2","properties":{},"children":[{"type":"text","value":"tasks"}]},{"type":"text","value":"\n"},{"type":"element","tagName":"ul","properties":{},"children":[{"type":"text","value":"\n"},{"type":"element","tagName":"li","properties":{},"children":[{"type":"text","value":"Architectural solutions design for SPA application (Flax/Components/Pure/Containers)"}]},{"type":"text","value":"\n"},{"type":"element","tagName":"li","properties":{},"children":[{"type":"text","value":"Make smart and dumb Components (React.js)"}]},{"type":"text","value":"\n"},{"type":"element","tagName":"li","properties":{},"children":[{"type":"text","value":"Architectural solutions client store (Redux store)"}]},{"type":"text","value":"\n"},{"type":"element","tagName":"li","properties":{},"children":[{"type":"text","value":"Created Router for Application (modal/permissions/auth)"}]},{"type":"text","value":"\n"},{"type":"element","tagName":"li","properties":{},"children":[{"type":"text","value":"Fetching data from Rest API"}]},{"type":"text","value":"\n"}]}],"data":{"quirksMode":false}},"frontmatter":{"title":"Frontend-Developer","path":"/job/yondermusic","date":"01-February-2017 - 01-February-2018"}}},{"node":{"id":"0967223a-45fc-5916-854b-478f0206b908","htmlAst":{"type":"root","children":[{"type":"element","tagName":"h1","properties":{},"children":[{"type":"text","value":"Web-Developer"}]},{"type":"text","value":"\n"},{"type":"element","tagName":"h2","properties":{},"children":[{"type":"text","value":"info"}]},{"type":"text","value":"\n"},{"type":"element","tagName":"ul","properties":{},"children":[{"type":"text","value":"\n"},{"type":"element","tagName":"li","properties":{},"children":[{"type":"text","value":"Company: ООО “Белитсофт” (Smartmatic)"}]},{"type":"text","value":"\n"},{"type":"element","tagName":"li","properties":{},"children":[{"type":"text","value":"Project: Evote"}]},{"type":"text","value":"\n"},{"type":"element","tagName":"li","properties":{},"children":[{"type":"text","value":"Technical stack and tools: JavaScript(es6), React.js, Flux, SCSS, React-Bootstrap, Gulp.js/Webpack.js, yarn, lodash"}]},{"type":"text","value":"\n"}]},{"type":"text","value":"\n"},{"type":"element","tagName":"h2","properties":{},"children":[{"type":"text","value":"tasks"}]},{"type":"text","value":"\n"},{"type":"element","tagName":"ul","properties":{},"children":[{"type":"text","value":"\n"},{"type":"element","tagName":"li","properties":{},"children":[{"type":"text","value":"Creating animated anchors with requestAnimationFrame"}]},{"type":"text","value":"\n"},{"type":"element","tagName":"li","properties":{},"children":[{"type":"text","value":"Tuning and optimization of the project builder for server and client Application"}]},{"type":"text","value":"\n"},{"type":"element","tagName":"li","properties":{},"children":[{"type":"text","value":"Migration project builder from grunt/browserify to gulp.js/webpack@2"}]},{"type":"text","value":"\n"},{"type":"element","tagName":"li","properties":{},"children":[{"type":"text","value":"Create UI Components with React"}]},{"type":"text","value":"\n"}]}],"data":{"quirksMode":false}},"frontmatter":{"title":"Web-Developer","path":"/job/smartmatic","date":"01-November-2016 - 01-February-2017"}}},{"node":{"id":"1cf12d9a-89e2-51c3-88ab-2e09a81a9c9c","htmlAst":{"type":"root","children":[{"type":"element","tagName":"h1","properties":{},"children":[{"type":"text","value":"Frontend-Developer"}]},{"type":"text","value":"\n"},{"type":"element","tagName":"h2","properties":{},"children":[{"type":"text","value":"description"}]},{"type":"text","value":"\n"},{"type":"element","tagName":"ul","properties":{},"children":[{"type":"text","value":"\n"},{"type":"element","tagName":"li","properties":{},"children":[{"type":"text","value":"Company: ООО \"Валикс-Вэб\""}]},{"type":"text","value":"\n"},{"type":"element","tagName":"li","properties":{},"children":[{"type":"text","value":"Project: Zaochnik, Rmoney"}]},{"type":"text","value":"\n"},{"type":"element","tagName":"li","properties":{},"children":[{"type":"text","value":"Technical stack and tools: JavaScript, Angular.js(1.6), SCSS/SASS, Foundation.css, Gulp.js, npm, node.js (express.js , request.js), Git"}]},{"type":"text","value":"\n"}]},{"type":"text","value":"\n"},{"type":"element","tagName":"h2","properties":{},"children":[{"type":"text","value":"tasks"}]},{"type":"text","value":"\n"},{"type":"element","tagName":"ul","properties":{},"children":[{"type":"text","value":"\n"},{"type":"element","tagName":"li","properties":{},"children":[{"type":"text","value":"Validate users forms with native js and angular.js"}]},{"type":"text","value":"\n"},{"type":"element","tagName":"li","properties":{},"children":[{"type":"text","value":"Create directives for search articles, autocomplete"}]},{"type":"text","value":"\n"},{"type":"element","tagName":"li","properties":{},"children":[{"type":"text","value":"Development application marketing pages"}]},{"type":"text","value":"\n"},{"type":"element","tagName":"li","properties":{},"children":[{"type":"text","value":"Development of email templates"}]},{"type":"text","value":"\n"}]}],"data":{"quirksMode":false}},"frontmatter":{"title":"Frontend-developer","path":"/job/zaochnik","date":"01-November-2015 - 20-October-2016"}}}]}},"pageContext":{}}